messenger/__init__.py
messenger/fbtypes.py
messenger/header.py
messenger/login.py
messenger/logout.py
messenger/messenger.py
messenger/pull.py
messenger/utils.py
messenger/get/__init__.py
messenger/get/friends.py
messenger/get/message.py
messenger/get/threads.py
messenger/send/__init__.py
messenger/send/message.py
messenger/setting/__init__.py
messenger/setting/admin.py
messenger/setting/emoji.py
messenger/setting/nickname.py
messenger/setting/participant.py
messenger/setting/thread.py
messenger/setting/utils.py
messengerwrapper-0.0.1.dev1.dist-info/DESCRIPTION.rst
messengerwrapper-0.0.1.dev1.dist-info/METADATA
messengerwrapper-0.0.1.dev1.dist-info/RECORD
messengerwrapper-0.0.1.dev1.dist-info/WHEEL
messengerwrapper-0.0.1.dev1.dist-info/metadata.json
messengerwrapper-0.0.1.dev1.dist-info/top_level.txt
