Metadata-Version: 2.0
Name: messengerwrapper
Version: 0.0.1.dev1
Summary: An unofficial Facebook Messenger Wrapper for Python.
Home-page: https://github.com/brian41005/Python-Messenger-Wrapper.git
License: LICENSE
Platform: UNKNOWN
Classifier: Programming Language :: Python :: 3.5
Classifier: Programming Language :: Python :: 3.6
Classifier: Development Status :: 2 - Pre-Alpha
Classifier: License :: OSI Approved :: MIT License
Classifier: Topic :: Communications :: Chat
Requires-Python: >=3.5.2
Requires-Dist: requests (>=2.18.4)
Requires-Dist: bs4 (>=0.0.1)
Requires-Dist: lxml (>=4.2.3)
